pie_datasets/__init__.py
pie_datasets/builders/__init__.py
pie_datasets/builders/brat.py
pie_datasets/core/__init__.py
pie_datasets/core/builder.py
pie_datasets/core/dataset.py
pie_datasets/core/dataset_dict.py
pie_datasets/core/document_formatter.py
pie_datasets/document/__init__.py
pie_datasets/document/processing/__init__.py
pie_datasets/document/processing/generic.py
pie_datasets-0.11.0.dist-info/LICENSE
pie_datasets-0.11.0.dist-info/METADATA
pie_datasets-0.11.0.dist-info/WHEEL
pie_datasets-0.11.0.dist-info/RECORD
