Metadata-Version: 2.1
Name: pie-datasets
Version: 0.11.0
Summary: Building scripts for Python-IE Datasets
Home-page: https://github.com/arnebinder/pie-datasets
Author: Arne Binder
Author-email: arne.binder@dfki.de
Requires-Python: >=3.9,<4.0
Classifier: Framework :: Pytest
Classifier: Programming Language :: Python
Classifier: Programming Language :: Python :: 3
Classifier: Programming Language :: Python :: 3.9
Classifier: Programming Language :: Python :: 3.10
Classifier: Programming Language :: Python :: 3.11
Classifier: Programming Language :: Python :: 3 :: Only
Requires-Dist: datasets (>=2.14.0,<2.16.0)
Requires-Dist: fsspec (<2023.9.0)
Requires-Dist: huggingface-hub (>=0.24.0)
Requires-Dist: numpy (<2.0.0)
Requires-Dist: pie-core (>=0.2.0,<0.4.0)
Requires-Dist: pyarrow (>=13,<14)
Project-URL: Bug Tracker, https://github.com/arnebinder/pie-datasets/issues
Project-URL: Changelog, https://github.com/arnebinder/pie-datasets/releases
Project-URL: Repository, https://github.com/arnebinder/pie-datasets
